LICENSE
MANIFEST.in
README.rst
setup.cfg
setup.py
bin/pfmisc
pfmisc/Auth.py
pfmisc/C_snode.py
pfmisc/C_stringCore.py
pfmisc/__init__.py
pfmisc/_colors.py
pfmisc/debug.py
pfmisc/dgmsocket.py
pfmisc/error.py
pfmisc/local_ip.py
pfmisc/message.py
pfmisc/other.py
pfmisc/pfmisc.py
pfmisc/pfmisc2.py
pfmisc.egg-info/PKG-INFO
pfmisc.egg-info/SOURCES.txt
pfmisc.egg-info/dependency_links.txt
pfmisc.egg-info/not-zip-safe
pfmisc.egg-info/requires.txt
pfmisc.egg-info/top_level.txt