Metadata-Version: 2.1
Name: pfmisc
Version: 2.2.14
Summary: Misc utilities for FNNDSC python repos
Home-page: https://github.com/FNNDSC/pfmisc
Author: Rudolph Pienaar
Author-email: rudolph.pienaar@gmail.com
License: MIT
License-File: LICENSE
